{
  "name": "Ricky Rowe",
  "age": 40,
  "address": {
    "street": "Owuca Court",
    "city": "Ekgase",
    "state": "NE",
    "zip": "21964"
  },
  "contact": {
    "phone": "(818) 744-3141",
    "servicePhone": "800851663"
  },
  "birthday": "1978-01-05T10:54:32.447Z",
  "ip": "251.202.40.247",
  "foo": "bar",
  "profile": {
    "about": "Loeha nulo izekoc keluste winsabsi cuewusos he po nuv pocakgoc nicoho fejil tufrevnu nuvem. Ab tihahuh if pejo hem gowot biwu naolpuj sezaseep je mahehove ir. Purkobit peopli ran seelihi baw afohieha emekiuvi ku nokow cap howuszo cucbile iwihuz. Ku vu vauragu tuwju zivicefa hifwej lemaztip mokukru bemuse habtumig harhir telbo.",
    "bio": "Rujis gitewan gadag tujoc onugaor isubkik mohodzig kosi jublimi cid po ka. Ava datab pojo zuctewgu ijkuhla rasope cin la wudurajas ejwa rek isnewmov ketwuus. Badam okjobu tibo fe ok has kecucir fi nuhtarnid keh owukiebi humi messujid hobpode caon bu ot gawki. Bujinjoj jonluna za od laf wafcuwtik vobam sirah vitukgid hiw bawajila zeh je."
  },
  "apiKey": "3875801116db94749d412bfbccbe9340f6fb21628c9940d188aa17e24d365588",
  "currency": {
    "code": "SOS",
    "name": "Somalia Shilling"
  }
}