{
  "name": "Minnie Shaw",
  "age": 32,
  "address": {
    "street": "Viara Park",
    "city": "Aneopmu",
    "state": "IA",
    "zip": "32646"
  },
  "contact": {
    "phone": "(548) 445-2232",
    "servicePhone": "800395513"
  },
  "birthday": "1971-08-19T11:44:23.438Z",
  "ip": "100.81.131.87",
  "foo": "bar",
  "profile": {
    "about": "Pena hakozufe evefso dodzew po dakodiwa mutekfa joehsus nomad abloj abgo hafot runsudkuh took je culca fobeki mohew. Rola pofvida su salagod vin wilo wotpot ruw te ecdu cek gaipo di. Vom tobaspid hefpehot zirehanol an imo pa rukjacec memlomo rad eha udawef ga si. Dizup ohut owwi sah oro odife wifubuc mol atgip ewamejwi wod fen cuc miadonan bu nilgeihe. Momce mulbobilu es ha zefrun vabzica ajhigmit kocuvih ocpid eno wudbekfog dunedka tuw sal cicov zoohsos su. Delaimo pele er ota nazijkuj cif wezdel fijo vokkuzror jeoto kuhifi dap faileje.",
    "bio": "Mefcar gijek ujinu kehtas duvu besi copfal ohizek zulhe laru gevgain fuh hafba imvot. Jajuzceb pima wohe mi kimo ki upbibez dapevmis emnaruj uro ka kolbudzog cik uvu omifu od gahi. Barna inucitim jolar vuhcuhani datwo vuh but enuconboh utti hif rourec hohef uhnaldes ma idibu fitcabhad."
  },
  "apiKey": "adef98570619e9acd44cf578564c6d1282e8fe087e25a064fb347b17397557b2",
  "currency": {
    "code": "BDT",
    "name": "Bangladesh Taka"
  }
}